cozyblanket/__init__.py
cozyblanket/cli.py
cozyblanket/connection.py
cozyblanket/utils.py
cozyblanket-2.0.1.dist-info/METADATA
cozyblanket-2.0.1.dist-info/WHEEL
cozyblanket-2.0.1.dist-info/licenses/LICENSE
cozyblanket-2.0.1.dist-info/RECORD
