Metadata-Version: 2.1
Name: cozyblanket
Version: 2.0.1
Summary: CozyBlanket's remote network control API implementation.
Project-URL: Homepage, https://sparseal.com/cozyblanket/network
Author-email: Joan Fons Sanchez <joan@sparseal.com>, Pablo Dobarro Peña <pablo@sparseal.com>
License: Copyright (c) 2022 Sparseal SL
License-File: LICENSE
Classifier: License :: OSI Approved :: MIT License
Classifier: Operating System :: OS Independent
Classifier: Programming Language :: Python :: 3
Requires-Python: >=3.7
